mcp_naver/__init__.py
mcp_naver/server.py
mcp_naver/hosts/__init__.py
mcp_naver/hosts/claude_desktop.py
mcp_naver/hosts/cursor.py
mseep_mcp_naver-0.1.9.dist-info/METADATA
mseep_mcp_naver-0.1.9.dist-info/WHEEL
mseep_mcp_naver-0.1.9.dist-info/entry_points.txt
mseep_mcp_naver-0.1.9.dist-info/licenses/LICENSE
mseep_mcp_naver-0.1.9.dist-info/RECORD
